{
  "context": "visitors",
  "description": "Gestión de visitantes V1",
  "controllers": [
    {
      "name": "VisitorController",
      "context": "visitors",
      "baseUrl": "visitor",
      "description": "Controller sin descripción",
      "tags": [
        "Visitantes"
      ],
      "endpoints": [
        {
          "method": "GET",
          "path": "/visitor/me",
          "summary": "Obtener información del visitante autenticado",
          "description": "Retorna la información del visitante basada en el token JWT autenticado. Permite al visitante obtener su propio perfil sin necesidad de conocer su ID.",
          "tags": [],
          "auth": {
            "required": true,
            "roles": [
              "visitor"
            ],
            "bearer": true
          },
          "parameters": {},
          "responses": [],
          "examples": {}
        },
        {
          "method": "GET",
          "path": "/visitor/:visitorId",
          "summary": "Obtener datos del visitante por ID",
          "description": "Obtiene los datos del visitante a partir del ID en la URL",
          "tags": [],
          "auth": {
            "required": true,
            "roles": [
              "commercial"
            ],
            "bearer": true
          },
          "parameters": {},
          "responses": [],
          "examples": {}
        },
        {
          "method": "PUT",
          "path": "/visitor/:visitorId/email",
          "summary": "Actualizar email del visitante",
          "description": "Actualiza el correo electrónico del visitante",
          "tags": [],
          "auth": {
            "required": true,
            "roles": [
              "commercial"
            ],
            "bearer": true
          },
          "parameters": {},
          "responses": [],
          "examples": {}
        },
        {
          "method": "PUT",
          "path": "/visitor/:visitorId/name",
          "summary": "Actualizar nombre del visitante",
          "description": "Actualiza el nombre del visitante",
          "tags": [],
          "auth": {
            "required": true,
            "roles": [
              "commercial"
            ],
            "bearer": true
          },
          "parameters": {},
          "responses": [],
          "examples": {}
        },
        {
          "method": "PUT",
          "path": "/visitor/:visitorId/tel",
          "summary": "Actualizar teléfono del visitante",
          "description": "Actualiza el número de teléfono del visitante",
          "tags": [],
          "auth": {
            "required": true,
            "roles": [
              "commercial"
            ],
            "bearer": true
          },
          "parameters": {},
          "responses": [],
          "examples": {}
        }
      ],
      "filePath": "src/context/visitors/infrastructure/controllers/visitor.controller.ts"
    }
  ],
  "summary": {
    "controllersCount": 1,
    "endpointsCount": 5
  }
}